MANIFEST.in
README.rst
setup.py
nsms/__init__.py
nsms/__init__.pyc
nsms/__init__.py~
nsms.egg-info/PKG-INFO
nsms.egg-info/SOURCES.txt
nsms.egg-info/dependency_links.txt
nsms.egg-info/not-zip-safe
nsms.egg-info/top_level.txt
nsms/parser/__init__.py
nsms/parser/parser.py
nsms/parser/tests.py
nsms/skeleton/pip-requires.txt
nsms/skeleton/pip-requires.txt~
nsms/skeleton/project/__init__.py
nsms/skeleton/project/manage.py
nsms/skeleton/project/settings.py.dev
nsms/skeleton/project/settings.py.mysql
nsms/skeleton/project/settings.py.prod
nsms/skeleton/project/settings_common.py
nsms/skeleton/project/translation.py
nsms/skeleton/project/urls.py
nsms/skeleton/project/dashboard/__init__.py
nsms/skeleton/project/dashboard/tests.py
nsms/skeleton/project/dashboard/urls.py
nsms/skeleton/project/dashboard/views.py
nsms/skeleton/project/mileage/__init__.py
nsms/skeleton/project/mileage/app.py
nsms/skeleton/project/mileage/models.py
nsms/skeleton/project/mileage/tests.py
nsms/skeleton/project/mileage/urls.py
nsms/skeleton/project/mileage/views.py
nsms/skeleton/static/base.html
nsms/skeleton/static/css/styles.css
nsms/skeleton/templates/base.html
nsms/skeleton/templates/dashboard/index.html
nsms/skeleton/templates/router/index.html
nsms/text/__init__.py
nsms/text/models.py
nsms/text/tests.py
nsms/text/urls.py
nsms/text/views.py
scripts/start-nsms