Metadata-Version: 1.0
Name: nsms
Version: 1.0.4
Summary: Provides a skeleton RapidSMS project using Nyaruka's best practices.
Home-page: http://github.com/nyaruka/nsms
Author: Nicolas Pottier
Author-email: code@nyaruka.com
License: BSD
Download-URL: http://github.com/nyaruka/nsms/downloads
Platform: UNKNOWN
Classifier: Development Status :: 4 - Beta
Classifier: Environment :: Web Environment
Classifier: Intended Audience :: Developers
Classifier: License :: OSI Approved :: BSD License
Classifier: Operating System :: OS Independent
Classifier: Programming Language :: Python
Classifier: Framework :: Django
